[
  {
    "id": "lypred-001",
    "question": "리비아에서 2030년까지 통합 선거가 실시될까?",
    "yesPool": 3500,
    "noPool": 16500,
    "deadline": "2030-12-31"
  },
  {
    "id": "lypred-002",
    "question": "리비아 동서 정부가 2028년까지 실질적으로 통합될까?",
    "yesPool": 2000,
    "noPool": 18000,
    "deadline": "2028-12-31"
  },
  {
    "id": "lypred-003",
    "question": "리비아 원유 생산이 2027년까지 일 200만 배럴을 회복할까?",
    "yesPool": 4000,
    "noPool": 16000,
    "deadline": "2027-12-31"
  },
  {
    "id": "lypred-004",
    "question": "외국 용병·무장세력이 2028년까지 리비아에서 완전히 철수할까?",
    "yesPool": 1500,
    "noPool": 18500,
    "deadline": "2028-12-31"
  }
]
