[
  {
    "id": "plevt-001",
    "title": "밸푸어 선언·유대 민족 국가 지지",
    "description": "영국 외무장관 아서 밸푸어가 로스차일드 경에게 보낸 서한으로, 팔레스타인에 유대 민족의 국가 건설을 지지한다고 선언했다. '기존 비유대 공동체의 권리를 침해하지 않는다'는 단서를 달았으나, 팔레스타인 아랍인의 동의 없이 이루어진 결정이었다.",
    "date": "1917-11-02",
    "category": "외교",
    "confidence": 95,
    "status": "verified"
  },
  {
    "id": "plevt-002",
    "title": "유엔 분할 결의안 181호 채택",
    "description": "유엔 총회가 팔레스타인을 유대 국가와 아랍 국가로 분할하는 결의안 181호를 33대 13으로 채택했다. 유대 측은 수락했으나 아랍 측은 전면 거부했다. 예루살렘은 국제 관할로 지정되었다.",
    "date": "1947-11-29",
    "category": "외교",
    "confidence": 95,
    "status": "verified"
  },
  {
    "id": "plevt-003",
    "title": "이스라엘 건국 선언·1차 중동전쟁",
    "description": "다비드 벤구리온이 이스라엘 독립을 선언하자 이집트, 시리아, 요르단, 이라크, 레바논 5개 아랍국이 즉시 침공하며 1차 중동전쟁이 발발했다. 이스라엘은 분할안보다 넓은 영토를 확보하며 승리했다.",
    "date": "1948-05-14",
    "category": "군사",
    "confidence": 95,
    "status": "verified"
  },
  {
    "id": "plevt-004",
    "title": "나크바·70만 팔레스타인 난민 발생",
    "description": "1차 중동전쟁 과정에서 약 70만 팔레스타인인이 고향에서 추방되거나 피난하는 '나크바(대재앙)'가 발생했다. 수백 개 마을이 파괴되었으며, 난민 문제는 오늘날까지 해결되지 않은 핵심 쟁점으로 남아있다.",
    "date": "1949-03-10",
    "category": "사회",
    "confidence": 90,
    "status": "verified"
  },
  {
    "id": "plevt-005",
    "title": "6일 전쟁·서안·가자·골란 점령",
    "description": "이스라엘이 이집트·시리아·요르단에 대한 선제공격으로 단 6일 만에 시나이 반도, 서안지구, 가자지구, 골란고원을 점령했다. 이 전쟁으로 이스라엘 영토는 3배로 확장되었고, 수백만 팔레스타인인이 군사 점령 하에 놓이게 되었다.",
    "date": "1967-06-05",
    "category": "군사",
    "confidence": 95,
    "status": "verified"
  },
  {
    "id": "plevt-006",
    "title": "욤키푸르 전쟁·1차 오일쇼크 촉발",
    "description": "이집트와 시리아가 유대교 속죄일(욤키푸르)에 이스라엘을 기습 공격했다. 초기 아랍 측의 성공 후 이스라엘이 역전했으며, OPEC의 석유 금수 조치로 1차 오일쇼크가 발생하여 유가가 4배 폭등했다.",
    "date": "1973-10-06",
    "category": "군사",
    "confidence": 95,
    "status": "verified"
  },
  {
    "id": "plevt-007",
    "title": "캠프 데이비드 협정·이집트-이스라엘 평화",
    "description": "카터 미국 대통령의 중재로 이집트 사다트 대통령과 이스라엘 베긴 총리가 캠프 데이비드에서 역사적 평화 협정을 체결했다. 이집트는 시나이 반도를 반환받고 최초의 아랍-이스라엘 평화 조약을 맺었다.",
    "date": "1978-09-17",
    "category": "외교",
    "confidence": 95,
    "status": "verified"
  },
  {
    "id": "plevt-008",
    "title": "1차 인티파다 발발",
    "description": "가자지구 자발리야 난민촌에서 이스라엘 군용 트럭이 팔레스타인 노동자를 치어 사망시킨 사건을 계기로 20년간 축적된 점령에 대한 팔레스타인 대중 봉기(인티파다)가 폭발했다. 돌팔매와 총파업 등 비무장 저항이 중심이었다.",
    "date": "1987-12-09",
    "category": "사회",
    "confidence": 90,
    "status": "verified"
  },
  {
    "id": "plevt-009",
    "title": "오슬로 협정·PLO-이스라엘 상호 인정",
    "description": "노르웨이의 비밀 중재로 이스라엘과 PLO가 워싱턴에서 역사적 오슬로 협정에 서명했다. 라빈 총리와 아라파트 의장이 악수를 나누며 상호 인정하고, 5년 내 최종지위 협상을 완료하기로 합의했다.",
    "date": "1993-09-13",
    "category": "외교",
    "confidence": 95,
    "status": "verified"
  },
  {
    "id": "plevt-010",
    "title": "2차 인티파다(알아크사 인티파다) 발발",
    "description": "오슬로 프로세스가 교착되고 캠프 데이비드 정상회담이 결렬된 직후, 이스라엘 야당 지도자 샤론이 알아크사 모스크(성전산)를 방문한 것을 계기로 2차 인티파다가 발발했다. 자살폭탄 테러와 군사적 진압으로 양측 수천 명이 사망했다.",
    "date": "2000-09-28",
    "category": "군사",
    "confidence": 90,
    "status": "verified"
  },
  {
    "id": "plevt-011",
    "title": "이스라엘 가자 철수·하마스 선거 승리",
    "description": "샤론 총리가 38년간의 가자지구 점령을 일방적으로 종료하고 8,000명의 유대인 정착민을 철수시켰다. 이듬해 팔레스타인 총선에서 하마스가 파타를 꺾고 승리하여 가자를 장악했다.",
    "date": "2005-08-15",
    "category": "외교",
    "confidence": 90,
    "status": "verified"
  },
  {
    "id": "plevt-012",
    "title": "가자 전쟁(캐스트 레드 작전) 시작",
    "description": "하마스의 로켓 공격에 대한 보복으로 이스라엘이 가자지구에 대규모 군사 작전(캐스트 레드)을 개시했다. 22일간의 공격으로 팔레스타인 측 1,400명 이상이 사망하여 국제적 비난을 받았다.",
    "date": "2008-12-27",
    "category": "군사",
    "confidence": 90,
    "status": "verified"
  },
  {
    "id": "plevt-013",
    "title": "가자 휴전 Phase 2 교착",
    "description": "2025년 1월 가자 휴전 1단계가 발효되었으나, 영구 휴전과 이스라엘군 완전 철수를 포함하는 2단계 협상이 교착 상태에 빠졌다. 이스라엘은 하마스 잔존 세력 제거를 주장하며 철수를 거부했다.",
    "date": "2026-01-15",
    "category": "외교",
    "confidence": 85,
    "status": "verified"
  },
  {
    "id": "plevt-014",
    "title": "이란 전쟁으로 가자 인도적 위기 심화",
    "description": "2026년 2월 미-이스라엘의 이란 공격과 후속 지역 전쟁으로 국제사회의 관심이 분산되면서 가자 지구 인도적 지원이 급감했다. 200만 주민의 식량·의약품 부족이 극한에 달했다.",
    "date": "2026-03-01",
    "category": "사회",
    "confidence": 80,
    "status": "verified"
  }
]
