[
  {
    "id": "uevt-001",
    "title": "부다페스트 각서 서명, 우크라이나 핵무기 포기",
    "description": "우크라이나가 구소련으로부터 물려받은 핵무기를 러시아에 반환하는 대가로, 미국·영국·러시아가 우크라이나의 영토 보전과 주권을 보장하는 안전보장 각서에 서명.",
    "date": "1994-12-05",
    "category": "외교",
    "confidence": 97,
    "status": "verified"
  },
  {
    "id": "uevt-002",
    "title": "오렌지 혁명, 친서방 유셴코 대통령 당선",
    "description": "대선 부정선거에 항의하는 대규모 시민 시위로 친러 야누코비치의 당선이 무효화되고, 친서방 유셴코가 대통령에 당선. 우크라이나의 서방 지향 전환점.",
    "date": "2004-11-22",
    "category": "사회",
    "confidence": 95,
    "status": "verified"
  },
  {
    "id": "uevt-003",
    "title": "나토 부쿠레슈티 정상회의, 우크라이나 가입 약속",
    "description": "나토 정상회의에서 우크라이나와 조지아가 '언젠가 나토 회원국이 될 것'이라는 선언 채택. 러시아는 이를 직접적 안보 위협으로 간주하며 강력 반발.",
    "date": "2008-04-03",
    "category": "외교",
    "confidence": 95,
    "status": "verified"
  },
  {
    "id": "uevt-004",
    "title": "야누코비치, EU 연합협정 서명 거부",
    "description": "대통령 야누코비치가 EU와의 연합협정 서명을 돌연 거부하고 러시아와의 경제 협력을 선택. 이에 분노한 시민들의 대규모 시위(유로마이단)가 시작.",
    "date": "2013-11-21",
    "category": "외교",
    "confidence": 97,
    "status": "verified"
  },
  {
    "id": "uevt-005",
    "title": "유로마이단 혁명, 야누코비치 축출",
    "description": "3개월간의 대규모 시위 끝에 야누코비치가 러시아로 도주. 의회가 대통령직 해임을 선언하고 과도정부 수립. 100명 이상 시위대 사망.",
    "date": "2014-02-22",
    "category": "사회",
    "confidence": 95,
    "status": "verified"
  },
  {
    "id": "uevt-006",
    "title": "러시아, 크림반도 병합",
    "description": "러시아가 '신원불명 무장세력(녹색 군인)'을 동원해 크림반도를 장악한 뒤, 주민투표를 실시하고 크림반도 병합 조약 서명. 국제사회 광범위한 비난과 제재 시작.",
    "date": "2014-03-18",
    "category": "군사",
    "confidence": 97,
    "status": "verified"
  },
  {
    "id": "uevt-007",
    "title": "돈바스 분리주의 무장봉기",
    "description": "도네츠크·루한스크에서 친러 무장세력이 정부 건물을 점거하고 인민공화국 선포. 우크라이나군과의 교전으로 동부 전쟁 시작.",
    "date": "2014-04-12",
    "category": "군사",
    "confidence": 92,
    "status": "verified"
  },
  {
    "id": "uevt-008",
    "title": "민스크 II 협정 체결",
    "description": "프랑스·독일 중재로 우크라이나와 러시아가 즉각 휴전, 중화기 철수, 돈바스 지역 특별지위 부여 등을 합의. 그러나 양측 모두 핵심 조항 이행 실패.",
    "date": "2015-02-12",
    "category": "외교",
    "confidence": 95,
    "status": "verified"
  },
  {
    "id": "uevt-009",
    "title": "러시아, 나토에 안보 최후통첩 발표",
    "description": "러시아가 나토의 동진 중단, 우크라이나·조지아 가입 불허, 동유럽 나토 병력 철수 등을 요구하는 조약 초안 공개. 사실상 최후통첩 성격.",
    "date": "2021-12-17",
    "category": "외교",
    "confidence": 95,
    "status": "verified"
  },
  {
    "id": "uevt-010",
    "title": "러시아, 우크라이나 전면 침공 개시",
    "description": "푸틴이 '특별군사작전'을 선포하며 우크라이나 전역에 대한 미사일 공격과 지상군 투입 시작. 키이우 포위 시도, 서방의 대규모 무기 지원과 경제 제재 개시.",
    "date": "2022-02-24",
    "category": "군사",
    "confidence": 99,
    "status": "verified"
  },
  {
    "id": "uevt-011",
    "title": "러시아, 우크라이나 4개주 병합 선언",
    "description": "러시아가 도네츠크·루한스크·자포리자·헤르손 4개주에서 주민투표를 실시하고 러시아 연방 편입을 선언. UN 총회에서 143개국이 병합 무효 결의.",
    "date": "2022-09-30",
    "category": "군사",
    "confidence": 97,
    "status": "verified"
  },
  {
    "id": "uevt-012",
    "title": "스위스 뷔르겐슈토크 평화 정상회의",
    "description": "스위스에서 90개국 이상이 참가한 우크라이나 평화 정상회의 개최. 핵안전, 식량안보, 포로 교환 등 논의. 러시아 미참가, 중국도 불참.",
    "date": "2024-06-15",
    "category": "외교",
    "confidence": 95,
    "status": "verified"
  },
  {
    "id": "uevt-013",
    "title": "미-우크라이나-러시아 3자 평화회담",
    "description": "미국 특사 위트코프 중재로 우크라이나-러시아-미국 3자 평화회담이 진행 중이다. 그러나 러시아 점령 영토 문제 등 핵심 쟁점은 미해결 상태다.",
    "date": "2026-03-10",
    "category": "외교",
    "confidence": 85,
    "status": "verified"
  },
  {
    "id": "uevt-014",
    "title": "우크라이나, 2023년 이후 첫 영토 수복",
    "description": "우크라이나군이 자포리자 지역에서 2023년 이후 처음으로 의미 있는 영토를 수복했다. 4주간 러시아군 57평방마일 후퇴. 드니프로페트로우스크 동부에서도 반격 성공.",
    "date": "2026-03-11",
    "category": "군사",
    "confidence": 85,
    "status": "verified"
  }
]
